[
  {
    "title": "Template News Article",
    "date": "2024-06-10",
    "image": "Files/002.jpg",
    "category": "General",
    "summary": "This is a template for a CE Geotech news article. You can write your content here using Markdown.",
    "markdown": "news/2024-06-10-template-article.txt"
  },

   {
    "title": "CE Geotech Strengthens UK Operations with Expanded Services",
    "date": "2025-09-12",
    "image": "Files/002.jpg",
    "category": "Announcements",
    "summary": "CE Geotech Strengthens UK Operations with Expanded Services",
    "markdown": "news/2025-09-12-StrengthenedUKOperations.txt"
  }
]